ncae_sdk/__init__.py
ncae_sdk/__version__.py
ncae_sdk/_async/__init__.py
ncae_sdk/_async/client.py
ncae_sdk/_async/endpoint.py
ncae_sdk/_async/session.py
ncae_sdk/_auth.py
ncae_sdk/_error.py
ncae_sdk/_http.py
ncae_sdk/_resource.py
ncae_sdk/_session.py
ncae_sdk/_sync/__init__.py
ncae_sdk/_sync/client.py
ncae_sdk/_sync/endpoint.py
ncae_sdk/_sync/session.py
ncae_sdk/_types.py
ncae_sdk/_util.py
ncae_sdk/endpoints/__init__.py
ncae_sdk/endpoints/_async/__init__.py
ncae_sdk/endpoints/_async/audit_log.py
ncae_sdk/endpoints/_async/awx_module.py
ncae_sdk/endpoints/_async/change_schedule.py
ncae_sdk/endpoints/_async/change_schedule_run.py
ncae_sdk/endpoints/_async/cmdb_entry.py
ncae_sdk/endpoints/_async/credential.py
ncae_sdk/endpoints/_async/device.py
ncae_sdk/endpoints/_async/device_group.py
ncae_sdk/endpoints/_async/device_model.py
ncae_sdk/endpoints/_async/ext_api_auth.py
ncae_sdk/endpoints/_async/ext_api_service.py
ncae_sdk/endpoints/_async/favourite.py
ncae_sdk/endpoints/_async/grafana_dashboard.py
ncae_sdk/endpoints/_async/grafana_system.py
ncae_sdk/endpoints/_async/influx_repository.py
ncae_sdk/endpoints/_async/influx_system.py
ncae_sdk/endpoints/_async/module.py
ncae_sdk/endpoints/_async/phase.py
ncae_sdk/endpoints/_async/phase_instance.py
ncae_sdk/endpoints/_async/report.py
ncae_sdk/endpoints/_async/service.py
ncae_sdk/endpoints/_async/service_instance.py
ncae_sdk/endpoints/_async/service_instance_log.py
ncae_sdk/endpoints/_async/shared_data_bucket.py
ncae_sdk/endpoints/_async/shared_data_subscriber.py
ncae_sdk/endpoints/_async/tag.py
ncae_sdk/endpoints/_async/tag_relation.py
ncae_sdk/endpoints/_async/tenant.py
ncae_sdk/endpoints/_async/transaction.py
ncae_sdk/endpoints/_async/upload_file.py
ncae_sdk/endpoints/_async/usage_log.py
ncae_sdk/endpoints/_async/user.py
ncae_sdk/endpoints/_sync/__init__.py
ncae_sdk/endpoints/_sync/audit_log.py
ncae_sdk/endpoints/_sync/awx_module.py
ncae_sdk/endpoints/_sync/change_schedule.py
ncae_sdk/endpoints/_sync/change_schedule_run.py
ncae_sdk-0.1.2.dist-info/licenses/LICENSE
ncae_sdk-0.1.2.dist-info/WHEEL
ncae_sdk-0.1.2.dist-info/METADATA
ncae_sdk-0.1.2.dist-info/RECORD
