Metadata-Version: 2.4
Name: ncae-sdk
Version: 0.1.2
Summary: Python SDK for Netcloud Automation Engine (NCAE)
Author: Netcloud AG
Author-email: Netcloud AG <ncae@netcloud.ch>
License-Expression: MIT
License-File: LICENSE
Requires-Dist: fastapi[standard]>=0.115.12
Requires-Dist: httpx>=0.28.1
Requires-Dist: pydantic>=2.11.3
Requires-Dist: pydantic-settings>=2.9.1
Requires-Python: >=3.9
